20-FSM/20-02-divby3/fsm-moor.v
module divideby3FSM(
    input clk,
    input reset, 
    output y
);

    reg [2:0] state, nextstate;

    parameter S0 = 2'b00;
    parameter S1 = 2'b01;
    parameter S2 = 2'b10;
    
    // state register
    always @(posedge clk or posedge reset) begin
        if (reset)  state <= S0;
        else        state <= nextstate;
    end
    // next state logic
    always @ (*)
        case (state)
            S0: nextstate = S1;
            S1: nextstate = S2;
            S2: nextstate = S0;
            default : nextstate = S0;
        endcase
    // output logic
    assign y = (state == S0);
endmodule

20-FSM/20-02-divby3/tb.v
`timescale 1ns/1ps
`include "fsm-moor.v"

module tb();
    // Inputs
    reg clk;
    reg reset;
    wire y;

    // Outputs
    wire [3:0] count;
    wire overflow;
    
    // Instantiate the Unit Under Test (UUT)
    divideby3FSM uut(   .clk(clk),
                        .reset(reset), 
                        .y(y)
                    );
    // Clock generation
    initial begin
        clk = 0;
        forever #10 clk = ~clk; 
    end
    
    // Stimulus
    initial begin
        // Initialize Inputs
        reset = 1;
        #20;
        reset = 0;
        #10; #10;#10;#10;#10;#10;#10;#10;#10;#10;#10; 
        #10; #10;#10;#10;#10;#10;#10;#10;#10;#10;#10;
        $finish;   
    end
    
    // Monitor the outputs
    initial begin
        $monitor("Time = %0t %b",  $time, y);
    end
    
    // Generate waveform file for debugging
    initial begin
        $dumpfile("dump.vcd");
        $dumpvars(0, tb);
    end
endmodule

20-FSM/20-02-divby3/dump.vcd
$date
	Tue May 27 15:16:07 2025
$end
$version
	Icarus Verilog
$end
$timescale
	1ps
$end
$scope module tb $end
$var wire 1 ! y $end
$var reg 1 " clk $end
$var reg 1 # reset $end
$scope module uut $end
$var wire 1 " clk $end
$var wire 1 # reset $end
$var wire 1 ! y $end
$var reg 3 $ nextstate [2:0] $end
$var reg 3 % state [2:0] $end
$upscope $end
$upscope $end
$enddefinitions $end
#0
$dumpvars
b0 %
b1 $
1#
0"
1!
$end
#10000
1"
#20000
0"
0#
#30000
b10 $
0!
b1 %
1"
#40000
0"
#50000
b0 $
b10 %
1"
#60000
0"
#70000
b1 $
1!
b0 %
1"
#80000
0"
#90000
b10 $
0!
b1 %
1"
#100000
0"
#110000
b0 $
b10 %
1"
#120000
0"
#130000
b1 $
1!
b0 %
1"
#140000
0"
#150000
b10 $
0!
b1 %
1"
#160000
0"
#170000
b0 $
b10 %
1"
#180000
0"
#190000
b1 $
1!
b0 %
1"
#200000
0"
#210000
b10 $
0!
b1 %
1"
#220000
0"
#230000
b0 $
b10 %
1"
