03-3 compfull2b/compfull2b.v
module compfull2b(
    input wire [1:0] a,
    input wire [1:0] b,
    output reg a_eq_b, // a = b
    output reg a_gt_b, // a > b
    output reg a_lt_b  // a < b
);

always @(*) begin
    if (a == b) begin
        a_eq_b = 1'b1; a_gt_b = 1'b0; a_lt_b = 1'b0;
    end
    else if(a > b) begin
        a_eq_b = 1'b0; a_gt_b = 1'b1; a_lt_b = 1'b0;
    end
    else begin
        a_eq_b = 1'b0; a_gt_b = 1'b0; a_lt_b = 1'b1;
    end
end

endmodule

03 comparator/03-3 compfull2b/tb.v
`timescale 1ns/1ps
`include "compfull2b.v"

module tb();
    reg [1:0] a;
    reg [1:0] b;
    wire a_eq_b;
    wire a_gt_b;
    wire a_lt_b;  // Fixed name from a_ls_b to match module port

    compfull2b uut(
        .a(a),
        .b(b),
        .a_eq_b(a_eq_b),
        .a_gt_b(a_gt_b),
        .a_lt_b(a_lt_b)  // Fixed connection from a_ls_b
    );

    initial begin
        // Dump waveform data (for GTKWave)
        $dumpfile("dump.vcd");   // Create a VCD file
        $dumpvars(0, tb);       // Dump all variables

        a = 2'b00; b = 2'b00;
        #10; b = 2'b01;
        #10; b = 2'b10;
        #10; b = 2'b11;

        a = 2'b01; b = 2'b00;
        #10; b = 2'b01;
        #10; b = 2'b10;
        #10; b = 2'b11;

        a = 2'b10; b = 2'b00;
        #10; b = 2'b01;
        #10; b = 2'b10;
        #10; b = 2'b11;

        a = 2'b11; b = 2'b00;
        #10; b = 2'b01;
        #10; b = 2'b10;
        #10; b = 2'b11;

        #10; a = 2'b00; b = 2'b00;
    end

    initial begin
        $monitor("a(%2b), b(%2b), a==b(%1b), a>b(%1b), a<b(%1b)", a, b, a_eq_b, a_gt_b, a_lt_b);
    end

endmodule

03-3 compfull2b/dump.vcd
$date
	Tue Apr 29 00:21:35 2025
$end
$version
	Icarus Verilog
$end
$timescale
	1ps
$end
$scope module tb $end
$var wire 1 ! a_lt_b $end
$var wire 1 " a_gt_b $end
$var wire 1 # a_eq_b $end
$var reg 2 $ a [1:0] $end
$var reg 2 % b [1:0] $end
$scope module uut $end
$var wire 2 & a [1:0] $end
$var wire 2 ' b [1:0] $end
$var reg 1 # a_eq_b $end
$var reg 1 " a_gt_b $end
$var reg 1 ! a_lt_b $end
$upscope $end
$upscope $end
$enddefinitions $end
#0
$dumpvars
b0 '
b0 &
b0 %
b0 $
1#
0"
0!
$end
#10000
1!
0#
b1 %
b1 '
#20000
b10 %
b10 '
#30000
0!
1"
b1 $
b1 &
b0 %
b0 '
#40000
0"
1#
b1 %
b1 '
#50000
1!
0#
b10 %
b10 '
#60000
0!
1"
b10 $
b10 &
b0 %
b0 '
#70000
b1 %
b1 '
#80000
0"
1#
b10 %
b10 '
#90000
1"
0#
b11 $
b11 &
b0 %
b0 '
#100000
b1 %
b1 '
#110000
b10 %
b10 '
#120000
0"
1#
b11 %
b11 '
#130000
b0 %
b0 '
b0 $
b0 &
