10-latch/10-2 dflipflop/dflipflop.v
module dflipflop(
    input wire d,        // Data input
    input wire clk,      // Clock input
    input wire en,       // Enable input
    input wire reset,    // Asynchronous reset input

    output reg q         // Output
);

    always @(posedge clk or posedge reset) begin
        if (reset) begin
            q <= 0; // Asynchronous reset to 0
        end 
        else if (en) begin
            q <= d; // If enabled, latch the data input on clock edge ('<=' non-blocking assignment)
        end
    end

endmodule

10-latch/10-2 dflipflop/tb.v
`timescale 1ns/1ps
`include "dflipflop.v"

module tb();
    // Testbench signals
    reg d;          // Data input
    reg clk;        // Clock input
    reg en;         // Enable input
    reg reset;      // Reset input
    wire q;         // Output from DUT
    
    // Instantiate the Device Under Test (DUT)
    dflipflop uut(
        .d(d),
        .clk(clk),
        .en(en),
        .reset(reset),
        .q(q)
    );
    
    initial begin
        $dumpfile("dump.vcd"); // Create a VCD file for waveform viewing
        $dumpvars(0, tb); // Dump all variables for waveform viewing
    end

    // Clock generation
    initial begin
        clk <= 0;
        forever begin
            #5 clk = ~clk; // Toggle clock every 5ns (100MHz)
        end 
    end
    
    // Monitor signals (moved out of the test sequence initial block)
    initial begin
        $monitor("t=%3d: d=%b, clk=%b, en=%b, reset=%b, q=%b", $time, d, clk, en, reset, q);
    end

    // Test sequence
    initial begin
        // Initialize inputs
        d = 0;
        en = 0;
        reset = 1; // Start with reset active
        
        // Release reset after 20ns
        #20 reset = 0;
        
        // Test case 1: Enable is low, d changes should not affect q
        #10 d = 1;
        #10 d = 0;
        #10 d = 1;
        
        // Test case 2: Enable high, d changes should be reflected in q on clock edges
        #10 en = 1;
        #10 d = 0;
        #10 d = 1;
        #10 d = 0;
        
        // Test case 3: Disable enable, d changes should not affect q
        #10 en = 0;
        #10 d = 1;
        #10 d = 0;
        
        // Test case 4: Test asynchronous reset while running
        #10 en = 1;
        #10 d = 1;
        #5 reset = 1; // Assert reset asynchronously
        #10 reset = 0; // Release reset
        
        // Test case 5: Final tests
        #10 d = 1;
        #10 en = 0;
        #10 d = 0;
        #10 en = 1;
        
        // End simulation after 200ns
        #10 $finish;
    end
    
endmodule

10-latch/10-2 dflipflop/dump.vcd
$date
	Tue May 20 14:29:50 2025
$end
$version
	Icarus Verilog
$end
$timescale
	1ps
$end
$scope module tb $end
$var wire 1 ! q $end
$var reg 1 " clk $end
$var reg 1 # d $end
$var reg 1 $ en $end
$var reg 1 % reset $end
$scope module uut $end
$var wire 1 " clk $end
$var wire 1 # d $end
$var wire 1 $ en $end
$var wire 1 % reset $end
$var reg 1 ! q $end
$upscope $end
$upscope $end
$enddefinitions $end
#0
$dumpvars
1%
0$
0#
0"
0!
$end
#5000
1"
#10000
0"
#15000
1"
#20000
0"
0%
#25000
1"
#30000
0"
1#
#35000
1"
#40000
0"
0#
#45000
1"
#50000
0"
1#
#55000
1"
#60000
0"
1$
#65000
1!
1"
#70000
0"
0#
#75000
0!
1"
#80000
0"
1#
#85000
1!
1"
#90000
0"
0#
#95000
0!
1"
#100000
0"
0$
#105000
1"
#110000
0"
1#
#115000
1"
#120000
0"
0#
#125000
1"
#130000
0"
1$
#135000
1"
#140000
0"
1#
#145000
1"
1%
#150000
0"
#155000
1!
1"
0%
#160000
0"
#165000
1"
#170000
0"
#175000
1"
0$
#180000
0"
#185000
1"
0#
#190000
0"
#195000
0!
1"
1$
