11-registers/11-02-register-siso/siso_reg.v

module siso_reg #(parameter N=8)
    (
        input clk,        // Clock signal
        input reset,      // Asynchronous reset (active-high)
        input data_in,    // Serial input
        output reg data_out  // Serial output
    );

    // Internal 4-bit shift register
    reg [N-1:0] shift_reg;

    always @(posedge clk or reset) begin
        if (reset) begin
            shift_reg <= 'b0;      // Clear the register on reset, eqv. shift_reg <= {N{'b0}}
            data_out  <= 1'b0;
        end else begin
            // Shift left (MSB is discarded, new bit enters LSB)
            shift_reg <= {shift_reg[N-2:0], data_in};
            // Output the MSB (serial output)
            data_out <= shift_reg[N-1];
        end
    end

endmodule

11-registers/11-02-register-siso/tb.v
`timescale 1ns/1ps
`include "siso_reg.v"

module tb();
    reg clk, reset, data_in;
    wire data_out;

    // Instantiate the SISO shift register
    siso_reg #(.N(8)) uut(
        .clk(clk),
        .reset(reset),
        .data_in(data_in),
        .data_out(data_out)
    );

    // Clock generation (10ns period)
    initial begin
        clk = 0;
        forever #5 clk = ~clk;
    end

    initial begin
        // Dump waveform data (for GTKWave)
        $dumpfile("dump.vcd");  // Create a VCD file
        $dumpvars(0, tb);       // Dump all variables
    end
    // Stimulus
    initial begin
        reset = 1;  // Apply reset
        data_in = 0;
        #10 reset = 0;  // Release reset

        // Shift in data: 1 → 0 → 1 → 1 (LSB first)
        data_in = 1; #10;  // 1st bit
        data_in = 0; #10;  // 2nd bit
        data_in = 1; #10;  // 3rd bit
        data_in = 1; #10;  // 4th bit
        data_in = 1; #10;  // 1st bit
        data_in = 0; #10;  // 2nd bit
        data_in = 1; #10;  // 3rd bit
        data_in = 1; #10;  // 4th bit
        data_in = 1; #10;  // 1st bit
        data_in = 0; #10;  // 2nd bit
        data_in = 1; #10;  // 3rd bit
        data_in = 1; #10;  // 4th bit

        // Observe output (should be delayed by 4 clocks)
        #20 $finish;
    end

    // Monitor outputs
    initial begin
        $monitor("Time = %0t: data_in = %b, data_out = %b, shift_reg = %b", 
                 $time, data_in, data_out, uut.shift_reg);
    end
endmodule

11-registers/11-02-register-siso/dump.vcd
$date
	Sat May 31 20:20:13 2025
$end
$version
	Icarus Verilog
$end
$timescale
	1ps
$end
$scope module tb $end
$var wire 1 ! data_out $end
$var reg 1 " clk $end
$var reg 1 # data_in $end
$var reg 1 $ reset $end
$scope module uut $end
$var wire 1 " clk $end
$var wire 1 # data_in $end
$var wire 1 $ reset $end
$var reg 1 ! data_out $end
$var reg 8 % shift_reg [7:0] $end
$upscope $end
$upscope $end
$enddefinitions $end
#0
$dumpvars
b0 %
1$
0#
0"
0!
$end
#5000
1"
#10000
b1 %
0"
1#
0$
#15000
b11 %
1"
#20000
0"
0#
#25000
b110 %
1"
#30000
0"
1#
#35000
b1101 %
1"
#40000
0"
#45000
b11011 %
1"
#50000
0"
#55000
b110111 %
1"
#60000
0"
0#
#65000
b1101110 %
1"
#70000
0"
1#
#75000
b11011101 %
1"
#80000
0"
#85000
1!
b10111011 %
1"
#90000
0"
#95000
b1110111 %
1"
#100000
0"
0#
#105000
0!
b11101110 %
1"
#110000
0"
1#
#115000
1!
b11011101 %
1"
#120000
0"
#125000
b10111011 %
1"
#130000
0"
#135000
b1110111 %
1"
#140000
0"
#145000
0!
b11101111 %
1"
