20-FSM/20-02-button_on_fsm/button.v
module button_on_a_FSM(
    input wire clk,          // Clock input
    input wire rst,          // Reset input
    input wire button,       // Button input
    output reg y            // Output signal (1 bit)
);
  /*
    reg [1:0] state, nextstate; // 2-bit state register

    // State encoding
    localparam S0 = 2'b00; // State 0: Button not pressed
    localparam S1 = 2'b01; // State 1: Button pressed
    localparam S2 = 2'b10; // State 2: Button released

    // Sequential logic for state transitions
    always @(posedge clk or posedge rst) begin
        if (rst) 
            state <= S0; // Reset to state S0
        else 
            state <= nextstate; // Transition to next state
    end
    
    always @(*) begin
        case (state)
            S0: nextstate = button ? S1 : S0; // Transition to S1 if button pressed
            S1: nextstate = button ? S1 : S2; // Stay in S1 if button pressed, else go to S2
            S2: nextstate = button ? S1 : S0; // Go back to S0 if button not pressed
            default: nextstate = S0; // Default case to avoid latches
        endcase
    end
    
    // Output logic
    always @(posedge clk or posedge rst) begin
        if (rst)
            y <= 0; // Reset output to low
        else 
            y <= (state == S1); // Output is high when in state S1, low otherwise
    end
    */

    parameter LED_ON = 1'b1; // LED on state
    parameter LED_OFF = 1'b0; // LED off state

    parameter STATE_LEDON = 1'b1; // State when LED is on
    parameter STATE_LEDOFF = 1'b0; // State when LED is off

    parameter BTN_PRESSED = 1'b1; // Button pressed state
    parameter BTN_RELEASED = 1'b0; // Button not pressed state



    reg state; // Register to hold LED status

    always @(posedge clk or posedge rst) begin
        if (rst) begin
          y <= LED_OFF; // Reset output to low
          state <= STATE_LEDOFF; // Reset state to LED off
        end
        else 
         case (state)
            STATE_LEDON: begin
                if (button==BTN_RELEASED) begin
                    state <= STATE_LEDOFF; // Transition to LED off state
                    y <= LED_OFF; // Set output to low
                end

            end

            STATE_LEDOFF: begin
                if (button==BTN_PRESSED) begin
                    state <= STATE_LEDON; // Transition to LED on state
                    y <= LED_ON; // Set output to high
                end
            end
            default: begin
                state <= STATE_LEDOFF; // Default case to avoid latches
                y <= LED_OFF; // Set output to low
            end
             

          endcase

    end
            
endmodule

20-FSM/20-02-button_on_fsm/tb.v
`timescale 1ns/1ps
`include "button.v"

module tb_button_on_a_FSM;

    reg clk;
    reg rst;
    reg button;
    wire y;

    // Instantiate the DUT
    button_on_a_FSM uut (
        .clk(clk),
        .rst(rst),
        .button(button),
        .y(y)
    );

    // Clock generation: 10ns period
    initial begin
        clk = 0;
        forever #5 clk = ~clk;
    end

    // Stimulus
    initial begin
        $dumpfile("dump.vcd");
        $dumpvars(0, tb_button_on_a_FSM);

        // Initialize
        rst = 1; button = 0;
        #12;
        rst = 0;

        // Press button (turn LED on)
        #10 button = 1;
        #20 button = 0; // Release button (turn LED off)
        #20 button = 1; // Press again (turn LED on)
        #10 button = 0; // Release (turn LED off)
        #15 button = 1; // Press again
        #10 button = 0; // Release

        // Test reset while button is pressed
        #10 button = 1;
        #5 rst = 1;
        #10 rst = 0;
        #10 button = 0;

        #20 $finish;
    end

    // Monitor
    initial begin
        $monitor("Time=%0t | rst=%b | button=%b | y=%b", $time, rst, button, y);
    end

endmodule

20-FSM/20-02-button_on_fsm/dump.vcd
$date
	Tue Jun 03 14:47:00 2025
$end
$version
	Icarus Verilog
$end
$timescale
	1ps
$end
$scope module tb_button_on_a_FSM $end
$var wire 1 ! y $end
$var reg 1 " button $end
$var reg 1 # clk $end
$var reg 1 $ rst $end
$scope module uut $end
$var wire 1 " button $end
$var wire 1 # clk $end
$var wire 1 $ rst $end
$var reg 1 % state $end
$var reg 1 ! y $end
$upscope $end
$upscope $end
$enddefinitions $end
#0
$dumpvars
0%
1$
0#
0"
0!
$end
#5000
1#
#10000
0#
#12000
0$
#15000
1#
#20000
0#
#22000
1"
#25000
1!
1%
1#
#30000
0#
#35000
1#
#40000
0#
#42000
0"
#45000
0!
0%
1#
#50000
0#
#55000
1#
#60000
0#
#62000
1"
#65000
1!
1%
1#
#70000
0#
#72000
0"
#75000
0!
0%
1#
#80000
0#
#85000
1#
#87000
1"
#90000
0#
#95000
1!
1%
1#
#97000
0"
#100000
0#
#105000
0!
0%
1#
#107000
1"
#110000
0#
#112000
1$
#115000
1#
#120000
0#
#122000
0$
#125000
1!
1%
1#
#130000
0#
#132000
0"
#135000
0!
0%
1#
