20-FSM/20-01-fsm/fsm-moor.v
module divideby3FSM(
  input wire clk, // Clock input
  input wire rst, // Reset input
  output y // Output signal (1 bit)
);

  reg [1:0] state,nextstate; // 2-bit state register

  // State encoding
  localparam S0 = 2'b00; // State 0
  localparam S1 = 2'b01; // State 1
  localparam S2 = 2'b10; // State 2

  // Sequential logic for state transitions
  always @(posedge clk or posedge rst) begin
    if (rst) 
      state <= S0; 
      else state <= nextstate;// Reset to state S0
    end
    
    always @(*)
      case (state)
        S0: nextstate = S1; // Transition from S0 to S1
        S1: nextstate = S2; // Transition from S1 to S2
        S2: nextstate = S0; // Transition from S2 back to S0
        default: state = S0; // Default case to avoid latches
      endcase
    
  // Output logic
  assign y = (state == S0); // Output is high when in state S0, low otherwise

  endmodule

20-FSM/20-01-fsm/tb.v
`timescale 1ns/1ps
`include "fsm-moor.v"

module tb;

    reg clk;
    reg rst;
    wire y;

    // Instantiate the DUT
    divideby3FSM uut (
        .clk(clk),
        .rst(rst),
        .y(y)
    );

    // Clock generation: 10ns period
    initial begin
        clk = 0;
        forever #5 clk = ~clk;
    end

    // Stimulus
    initial begin
        $dumpfile("dump.vcd");
        $dumpvars(0, tb);

        // Apply reset
        rst = 1;
        #12;
        rst = 0;

        // Run for several clock cycles
        repeat (12) begin
            #10;
            $display("Time=%0t | rst=%b | y=%b", $time, rst, y);
        end

        $finish;
    end

endmodule

20-FSM/20-01-fsm/dump.vcd
$date
	Tue May 27 15:28:49 2025
$end
$version
	Icarus Verilog
$end
$timescale
	1ps
$end
$scope module tb $end
$var wire 1 ! y $end
$var reg 1 " clk $end
$var reg 1 # rst $end
$scope module uut $end
$var wire 1 " clk $end
$var wire 1 # rst $end
$var wire 1 ! y $end
$var reg 2 $ nextstate [1:0] $end
$var reg 2 % state [1:0] $end
$upscope $end
$upscope $end
$enddefinitions $end
#0
$dumpvars
b0 %
b1 $
1#
0"
1!
$end
#5000
1"
#10000
0"
#12000
0#
#15000
b10 $
0!
b1 %
1"
#20000
0"
#25000
b0 $
b10 %
1"
#30000
0"
#35000
b1 $
1!
b0 %
1"
#40000
0"
#45000
b10 $
0!
b1 %
1"
#50000
0"
#55000
b0 $
b10 %
1"
#60000
0"
#65000
b1 $
1!
b0 %
1"
#70000
0"
#75000
b10 $
0!
b1 %
1"
#80000
0"
#85000
b0 $
b10 %
1"
#90000
0"
#95000
b1 $
1!
b0 %
1"
#100000
0"
#105000
b10 $
0!
b1 %
1"
#110000
0"
#115000
b0 $
b10 %
1"
#120000
0"
#125000
b1 $
1!
b0 %
1"
