06-fulladder/06-1 fulladder1b/fulladder1b.v
module fulladder1b(
    input wire a,        // First input bit
    input wire b,        // Second input bit
    input wire cin,      // Carry input
    output wire sum,     // Sum output
    output wire cout     // Carry output
);
    
assign {cout, sum} = a + b + cin; // Calculate sum and carry out
    
endmodule

06-fulladder/06-1 fulladder1b/tb.v
`timescale 1ps/1ps
`include "fulladder1b.v"

module tb ();
    reg a;        // First input bit
    reg b;        // Second input bit
    reg cin;      // Carry input
    wire sum;     // Sum output
    wire cout;    // Carry output

    // Instantiate the full adder module
    fulladder1b uut (
        .a(a),
        .b(b),
        .cin(cin),
        .sum(sum),
        .cout(cout)
    );

    initial begin
        //Dumpfile
        $dumpfile("dump.vcd");
        $dumpvars(0, tb);
        
        a = 1'b0; b = 1'b0; cin = 1'b0; #10; // Test case 1: a = 0, b = 0, cin = 0
        a = 1'b0; b = 1'b0; cin = 1'b1; #10; // Test case 2: a = 0, b = 0, cin = 1
        a = 1'b0; b = 1'b1; cin = 1'b0; #10; // Test case 3: a = 0, b = 1, cin = 0
        a = 1'b0; b = 1'b1; cin = 1'b1; #10; // Test case 4: a = 0, b = 1, cin = 1

        a = 1'b1; b = 1'b0; cin = 1'b0; #10; // Test case 5: a = 1, b = 0, cin = 0
        a = 1'b1; b = 1'b0; cin = 1'b1; #10; // Test case 6: a = 1, b = 0, cin = 1
        a = 1'b1; b = 1'b1; cin = 1'b0; #10; // Test case 7: a = 1, b = 1, cin = 0
        a = 1'b1; b = 1'b1; cin = 1'b1; #10; // Test case 8: a = 1, b = 1, cin = 1


    end

    initial begin

        // Test all combinations of inputs
        $monitor("Time: %0t | a: %b | b: %b | cin: %b | sum: %b | cout: %b", $time, a, b, cin, sum, cout);
    end

endmodule

06-fulladder/06-1 fulladder1b/dump.vcd
$date
	Tue Apr 29 14:13:53 2025
$end
$version
	Icarus Verilog
$end
$timescale
	1ps
$end
$scope module tb $end
$var wire 1 ! sum $end
$var wire 1 " cout $end
$var reg 1 # a $end
$var reg 1 $ b $end
$var reg 1 % cin $end
$scope module uut $end
$var wire 1 # a $end
$var wire 1 $ b $end
$var wire 1 % cin $end
$var wire 1 ! sum $end
$var wire 1 " cout $end
$upscope $end
$upscope $end
$enddefinitions $end
#0
$dumpvars
0%
0$
0#
0"
0!
$end
#10
1!
1%
#20
0%
1$
#30
0!
1"
1%
#40
0"
1!
0%
0$
1#
#50
0!
1"
1%
#60
0%
1$
#70
1!
1%
